{
  "pos_p0_q0": 0,
  "pos_p0_q1": 2,
  "pos_p0_q2": 3,
  "pos_p0_q3": 2,
  "pos_p0_q4": 3,
  "pos_p0_q5": 3,
  "pos_p0_q6": 2,
  "pos_p0_q7": 1,
  "pos_p0_q8": 2,
  "pos_p0_q9": 3,
  "pos_p0_q10": 3,
  "pos_p0_q11": 1,
  "pos_p0_q12": 2,
  "pos_p0_q13": 2,
  "pos_p0_q14": 3,
  "pos_p0_q15": 3,
  "pos_p0_q16": 3,
  "pos_p0_q17": 2,
  "pos_p0_q18": 2,
  "pos_p0_q19": 3,
  "pos_p0_q20": 3,
  "pos_p0_q21": 3,
  "pos_p0_q22": 3,
  "pos_p0_q23": 3,
  "pos_p0_q24": 2,
  "pos_p0_q25": 2,
  "pos_p0_q26": 3,
  "pos_p0_q27": 2,
  "pos_p0_q28": 3,
  "pos_p0_q29": 2,
  "pos_p1_q0": 3,
  "pos_p1_q1": 3,
  "pos_p1_q2": 3,
  "pos_p1_q3": 3,
  "pos_p1_q4": 3,
  "pos_p1_q5": 3,
  "pos_p1_q6": 3,
  "pos_p1_q7": 3,
  "pos_p1_q8": 3,
  "pos_p1_q9": 3,
  "pos_p1_q10": 3,
  "pos_p1_q11": 3,
  "pos_p1_q12": 3,
  "pos_p1_q13": 3,
  "pos_p1_q14": 3,
  "pos_p1_q15": 3,
  "pos_p1_q16": 3,
  "pos_p1_q17": 3,
  "pos_p1_q18": 3,
  "pos_p1_q19": 3,
  "pos_p1_q20": 3,
  "pos_p1_q21": 3,
  "pos_p1_q22": 3,
  "pos_p1_q23": 3,
  "pos_p1_q24": 3,
  "pos_p1_q25": 3,
  "pos_p1_q26": 3,
  "pos_p1_q27": 3,
  "pos_p1_q28": 3,
  "pos_p1_q29": 3,
  "pos_p2_q0": 3,
  "pos_p2_q1": 2,
  "pos_p2_q2": 3,
  "pos_p2_q3": 2,
  "pos_p2_q4": 3,
  "pos_p2_q5": 3,
  "pos_p2_q6": 3,
  "pos_p2_q7": 3,
  "pos_p2_q8": 3,
  "pos_p2_q9": 3,
  "pos_p2_q10": 3,
  "pos_p2_q11": 3,
  "pos_p2_q12": 2,
  "pos_p2_q13": 3,
  "pos_p2_q14": 2,
  "pos_p2_q15": 3,
  "pos_p2_q16": 3,
  "pos_p2_q17": 3,
  "pos_p2_q18": 2,
  "pos_p2_q19": 3,
  "pos_p2_q20": 3,
  "pos_p2_q21": 3,
  "pos_p2_q22": 3,
  "pos_p2_q23": 3,
  "pos_p2_q24": 3,
  "pos_p2_q25": 3,
  "pos_p2_q26": 3,
  "pos_p2_q27": 3,
  "pos_p2_q28": 3,
  "pos_p2_q29": 3,
  "pos_p3_q0": 2,
  "pos_p3_q1": 2,
  "pos_p3_q2": 3,
  "pos_p3_q3": 1,
  "pos_p3_q4": 3,
  "pos_p3_q5": 2,
  "pos_p3_q6": 2,
  "pos_p3_q7": 3,
  "pos_p3_q8": 2,
  "pos_p3_q9": 0,
  "pos_p3_q10": 3,
  "pos_p3_q11": 2,
  "pos_p3_q12": 2,
  "pos_p3_q13": 3,
  "pos_p3_q14": 2,
  "pos_p3_q15": 3,
  "pos_p3_q16": 3,
  "pos_p3_q17": 3,
  "pos_p3_q18": 2,
  "pos_p3_q19": 3,
  "pos_p3_q20": 3,
  "pos_p3_q21": 3,
  "pos_p3_q22": 3,
  "pos_p3_q23": 3,
  "pos_p3_q24": 3,
  "pos_p3_q25": 2,
  "pos_p3_q26": 3,
  "pos_p3_q27": 2,
  "pos_p3_q28": 3,
  "pos_p3_q29": 2,
  "pos_p4_q0": 3,
  "pos_p4_q1": 3,
  "pos_p4_q2": 3,
  "pos_p4_q3": 3,
  "pos_p4_q4": 3,
  "pos_p4_q5": 3,
  "pos_p4_q6": 3,
  "pos_p4_q7": 3,
  "pos_p4_q8": 3,
  "pos_p4_q9": 3,
  "pos_p4_q10": 3,
  "pos_p4_q11": 3,
  "pos_p4_q12": 3,
  "pos_p4_q13": 3,
  "pos_p4_q14": 3,
  "pos_p4_q15": 3,
  "pos_p4_q16": 3,
  "pos_p4_q17": 3,
  "pos_p4_q18": 3,
  "pos_p4_q19": 3,
  "pos_p4_q20": 3,
  "pos_p4_q21": 3,
  "pos_p4_q22": 3,
  "pos_p4_q23": 3,
  "pos_p4_q24": 3,
  "pos_p4_q25": 3,
  "pos_p4_q26": 3,
  "pos_p4_q27": 3,
  "pos_p4_q28": 3,
  "pos_p4_q29": 3,
  "default_p0_q0": 2,
  "default_p0_q1": 2,
  "default_p0_q2": 0,
  "default_p0_q3": 0,
  "default_p0_q4": 0,
  "default_p0_q5": 0,
  "default_p0_q6": 0,
  "default_p0_q7": 0,
  "default_p0_q8": 0,
  "default_p0_q9": 0,
  "default_p0_q10": 0,
  "default_p0_q11": 0,
  "default_p0_q12": 1,
  "default_p0_q13": 0,
  "default_p0_q14": 0,
  "default_p0_q15": 0,
  "default_p0_q16": 0,
  "default_p0_q17": 0,
  "default_p0_q18": 0,
  "default_p0_q19": 0,
  "default_p0_q20": 0,
  "default_p0_q21": 0,
  "default_p0_q22": 0,
  "default_p0_q23": 0,
  "default_p0_q24": 0,
  "default_p0_q25": 0,
  "default_p0_q26": 2,
  "default_p0_q27": 0,
  "default_p0_q28": 0,
  "default_p0_q29": 0,
  "default_p1_q0": 2,
  "default_p1_q1": 0,
  "default_p1_q2": 2,
  "default_p1_q3": 0,
  "default_p1_q4": 0,
  "default_p1_q5": 0,
  "default_p1_q6": 0,
  "default_p1_q7": 0,
  "default_p1_q8": 0,
  "default_p1_q9": 0,
  "default_p1_q10": 0,
  "default_p1_q11": 0,
  "default_p1_q12": 0,
  "default_p1_q13": 0,
  "default_p1_q14": 0,
  "default_p1_q15": 0,
  "default_p1_q16": 1,
  "default_p1_q17": 0,
  "default_p1_q18": 0,
  "default_p1_q19": 0,
  "default_p1_q20": 0,
  "default_p1_q21": 0,
  "default_p1_q22": 0,
  "default_p1_q23": 0,
  "default_p1_q24": 0,
  "default_p1_q25": 0,
  "default_p1_q26": 2,
  "default_p1_q27": 0,
  "default_p1_q28": 0,
  "default_p1_q29": 0,
  "default_p2_q0": 2,
  "default_p2_q1": 0,
  "default_p2_q2": 2,
  "default_p2_q3": 0,
  "default_p2_q4": 0,
  "default_p2_q5": 0,
  "default_p2_q6": 0,
  "default_p2_q7": 0,
  "default_p2_q8": 0,
  "default_p2_q9": 0,
  "default_p2_q10": 0,
  "default_p2_q11": 0,
  "default_p2_q12": 0,
  "default_p2_q13": 2,
  "default_p2_q14": 0,
  "default_p2_q15": 0,
  "default_p2_q16": 0,
  "default_p2_q17": 0,
  "default_p2_q18": 0,
  "default_p2_q19": 0,
  "default_p2_q20": 0,
  "default_p2_q21": 0,
  "default_p2_q22": 0,
  "default_p2_q23": 0,
  "default_p2_q24": 0,
  "default_p2_q25": 0,
  "default_p2_q26": 2,
  "default_p2_q27": 0,
  "default_p2_q28": 0,
  "default_p2_q29": 0,
  "default_p3_q0": 2,
  "default_p3_q1": 0,
  "default_p3_q2": 2,
  "default_p3_q3": 0,
  "default_p3_q4": 1,
  "default_p3_q5": 0,
  "default_p3_q6": 2,
  "default_p3_q7": 0,
  "default_p3_q8": 0,
  "default_p3_q9": 0,
  "default_p3_q10": 0,
  "default_p3_q11": 0,
  "default_p3_q12": 0,
  "default_p3_q13": 0,
  "default_p3_q14": 0,
  "default_p3_q15": 2,
  "default_p3_q16": 0,
  "default_p3_q17": 1,
  "default_p3_q18": 0,
  "default_p3_q19": 0,
  "default_p3_q20": 0,
  "default_p3_q21": 0,
  "default_p3_q22": 0,
  "default_p3_q23": 0,
  "default_p3_q24": 0,
  "default_p3_q25": 0,
  "default_p3_q26": 0,
  "default_p3_q27": 0,
  "default_p3_q28": 2,
  "default_p3_q29": 0,
  "default_p4_q0": 2,
  "default_p4_q1": 0,
  "default_p4_q2": 2,
  "default_p4_q3": 0,
  "default_p4_q4": 1,
  "default_p4_q5": 0,
  "default_p4_q6": 2,
  "default_p4_q7": 0,
  "default_p4_q8": 0,
  "default_p4_q9": 0,
  "default_p4_q10": 0,
  "default_p4_q11": 0,
  "default_p4_q12": 0,
  "default_p4_q13": 0,
  "default_p4_q14": 0,
  "default_p4_q15": 0,
  "default_p4_q16": 0,
  "default_p4_q17": 0,
  "default_p4_q18": 0,
  "default_p4_q19": 0,
  "default_p4_q20": 0,
  "default_p4_q21": 0,
  "default_p4_q22": 0,
  "default_p4_q23": 0,
  "default_p4_q24": 0,
  "default_p4_q25": 0,
  "default_p4_q26": 0,
  "default_p4_q27": 0,
  "default_p4_q28": 0,
  "default_p4_q29": 0
}